roles/__init__.py
roles/context.py
roles/django.py
roles/role.py
roles-1.0.0.dist-info/WHEEL
roles-1.0.0.dist-info/METADATA
roles-1.0.0.dist-info/RECORD
