Metadata-Version: 2.1
Name: roles
Version: 1.0.0
Summary: Role based software development
Home-page: https://github.com/amolenaar/roles
Keywords: role,DCI,data,context,interaction
Author: Arjan Molenaar
Author-email: gaphor@gmail.com
Maintainer: Arjan Molenaar
Maintainer-email: gaphor@gmail.com
Requires-Python: >=3.7,<4.0
Classifier: Development Status :: 4 - Beta
Classifier: Intended Audience :: Developers
Classifier: License :: OSI Approved :: BSD License
Classifier: Natural Language :: English
Classifier: Operating System :: OS Independent
Classifier: Programming Language :: Python
Classifier: Programming Language :: Python :: 3
Classifier: Programming Language :: Python :: 3.7
Classifier: Programming Language :: Python :: 3.8
Classifier: Topic :: Software Development :: Libraries
Project-URL: Documentation, https://github.com/amolenaar/roles
Project-URL: Repository, https://github.com/amolenaar/roles
